awscli_update/__init__.py
awscli_update/_version.py
awscli_update/update.py
awscli_update-0.1.12.data/scripts/awscli-update
awscli_update-0.1.12.dist-info/LICENSE
awscli_update-0.1.12.dist-info/METADATA
awscli_update-0.1.12.dist-info/WHEEL
awscli_update-0.1.12.dist-info/top_level.txt
awscli_update-0.1.12.dist-info/RECORD
