Metadata-Version: 2.1
Name: awscli-update
Version: 0.1.12
Summary: CLI tool to update AWS CLI 2
Home-page: https://github.com/x4121/awscli-update
Author: Armin Grodon
Author-email: me@armingrodon.de
License: MIT
Platform: UNKNOWN
Classifier: Environment :: Console
Classifier: Intended Audience :: Developers
Classifier: Intended Audience :: System Administrators
Classifier: License :: OSI Approved :: MIT License
Classifier: Operating System :: MacOS
Classifier: Operating System :: Microsoft :: Windows
Classifier: Operating System :: Unix
Classifier: Programming Language :: Python :: 3
Classifier: Topic :: System :: Installation/Setup
Classifier: Topic :: Utilities
License-File: LICENSE
Requires-Dist: requests (==2.26.0)
